{
    "geocoded_waypoints": [
        {
            "geocoder_status": "OK",
            "place_id": "ChIJ1z0B3FMvdTERw2vW-ZaYyfo",
            "types": [
                "establishment",
                "food",
                "point_of_interest",
                "restaurant"
            ]
        },
        {
            "geocoder_status": "OK",
            "place_id": "ChIJz_umALwvdTERk1NyG2asF5U",
            "types": [
                "premise"
            ]
        }
    ],
    "routes": [
        {
            "bounds": {
                "northeast": {
                    "lat": 10.7292194,
                    "lng": 106.7086657
                },
                "southwest": {
                    "lat": 10.7264535,
                    "lng": 106.6921217
                }
            },
            "copyrights": "Map data \u00a92020",
            "legs": [
                {
                    "distance": {
                        "text": "2.1 km",
                        "value": 2128
                    },
                    "duration": {
                        "text": "7 mins",
                        "value": 423
                    },
                    "end_address": "702 Nguy\u1ec5n V\u0103n Linh, T\u00e2n H\u01b0ng, Qu\u1eadn 7, Th\u00e0nh ph\u1ed1 H\u1ed3 Ch\u00ed Minh, Vietnam",
                    "end_location": {
                        "lat": 10.7290604,
                        "lng": 106.6921217
                    },
                    "start_address": "101 Nguy\u1ec5n \u0110\u1ee9c C\u1ea3nh, T\u00e2n Phong, Qu\u1eadn 7, Th\u00e0nh ph\u1ed1 H\u1ed3 Ch\u00ed Minh, Vietnam",
                    "start_location": {
                        "lat": 10.7264535,
                        "lng": 106.7086657
                    },
                    "steps": [
                        {
                            "distance": {
                                "text": "0.2 km",
                                "value": 204
                            },
                            "duration": {
                                "text": "1 min",
                                "value": 53
                            },
                            "end_location": {
                                "lat": 10.7282901,
                                "lng": 106.7086157
                            },
                            "html_instructions": "Head <b>north</b> on <b>Nguy\u1ec5n \u0110\u1ee9c C\u1ea3nh</b> toward <b>Ph\u1ea1m Th\u00e1i B\u01b0\u1eddng</b><div style=\"font-size:0.9em\">Pass by L\u1ea9u B\u0103ng Chuy\u1ec1n Kichi-Kichi (on the right)</div>",
                            "polyline": {
                                "points": "i_n`AephjSyDFuD@"
                            },
                            "start_location": {
                                "lat": 10.7264535,
                                "lng": 106.7086657
                            },
                            "travel_mode": "DRIVING"
                        },
                        {
                            "distance": {
                                "text": "77 m",
                                "value": 77
                            },
                            "duration": {
                                "text": "1 min",
                                "value": 22
                            },
                            "end_location": {
                                "lat": 10.728986,
                                "lng": 106.7086013
                            },
                            "html_instructions": "Continue straight past Gourmet Restaurant onto <b>B\u00f9i B\u1eb1ng \u0110o\u00e0n</b>/<wbr/><b>Nguy\u1ec5n \u0110\u1ee9c C\u1ea3nh</b>",
                            "maneuver": "straight",
                            "polyline": {
                                "points": "yjn`A{ohjSU@Y?{A@"
                            },
                            "start_location": {
                                "lat": 10.7282901,
                                "lng": 106.7086157
                            },
                            "travel_mode": "DRIVING"
                        },
                        {
                            "distance": {
                                "text": "1.4 km",
                                "value": 1427
                            },
                            "duration": {
                                "text": "4 mins",
                                "value": 248
                            },
                            "end_location": {
                                "lat": 10.7288642,
                                "lng": 106.69578
                            },
                            "html_instructions": "Turn <b>left</b> at <b>Nguy\u1ec5n V\u0103n Linh</b><div style=\"font-size:0.9em\">Pass by Ng\u00e2n H\u00e0ng Vietinbank Ph\u1ea1m V\u0103n Ngh\u1ecb (on the right)</div>",
                            "maneuver": "turn-left",
                            "polyline": {
                                "points": "eon`AwohjSW?U@HhJBzC?@FvI?h@@d@@~AAF@R?LBlBHjL@RBx@@j@?d@@dC@rE@hB@pAJvDB~@"
                            },
                            "start_location": {
                                "lat": 10.728986,
                                "lng": 106.7086013
                            },
                            "travel_mode": "DRIVING"
                        },
                        {
                            "distance": {
                                "text": "19 m",
                                "value": 19
                            },
                            "duration": {
                                "text": "1 min",
                                "value": 22
                            },
                            "end_location": {
                                "lat": 10.7290352,
                                "lng": 106.6957651
                            },
                            "html_instructions": "Turn <b>right</b> at Tr\u01b0\u1eddng \u0110\u1ea1i H\u1ecdc Rmit Nguy\u1ec5n V\u0103n Linh<div style=\"font-size:0.9em\">Restricted usage road</div>",
                            "maneuver": "turn-right",
                            "polyline": {
                                "points": "knn`As_fjSO@M?E?"
                            },
                            "start_location": {
                                "lat": 10.7288642,
                                "lng": 106.69578
                            },
                            "travel_mode": "DRIVING"
                        },
                        {
                            "distance": {
                                "text": "0.4 km",
                                "value": 401
                            },
                            "duration": {
                                "text": "1 min",
                                "value": 78
                            },
                            "end_location": {
                                "lat": 10.7290604,
                                "lng": 106.6921217
                            },
                            "html_instructions": "Turn <b>left</b><div style=\"font-size:0.9em\">Restricted usage road</div><div style=\"font-size:0.9em\">Pass by C\u1eeda h\u00e0ng \u0111\u1ed3 u\u1ed1ng Xiao Ban (on the right)</div><div style=\"font-size:0.9em\">Destination will be on the right</div>",
                            "maneuver": "turn-left",
                            "polyline": {
                                "points": "oon`Aq_fjS?@CBAB?DAF@D@H?J?R?RA`@?P?D?T?N@F@X@V?X?HCPAJ@H@HBR?L?NALCTAL?P@P@HBP?J@NAN?LAZ@f@AT?HCjA"
                            },
                            "start_location": {
                                "lat": 10.7290352,
                                "lng": 106.6957651
                            },
                            "travel_mode": "DRIVING"
                        }
                    ],
                    "traffic_speed_entry": [],
                    "via_waypoint": []
                }
            ],
            "overview_polyline": {
                "points": "i_n`AephjS_LJsB@U@HhJB|CF`KB`DNzPDdB@jDB|HLhGB~@O@S?EN@b@AzA@r@Bp@?b@E\\BRBp@GbAFx@AhA?|@CtA"
            },
            "summary": "Nguy\u1ec5n \u0110\u1ee9c C\u1ea3nh",
            "warnings": [],
            "waypoint_order": []
        }
    ],
    "status": "OK"
}